COPYING
MANIFEST.in
README.rst
setup.py
yellowhiggs/__init__.py
yellowhiggs/info.py
yellowhiggs/xsbr.py
yellowhiggs.egg-info/PKG-INFO
yellowhiggs.egg-info/SOURCES.txt
yellowhiggs.egg-info/dependency_links.txt
yellowhiggs.egg-info/top_level.txt
yellowhiggs/dat/br/2fermions.txt
yellowhiggs/dat/br/2gaugebosons.txt
yellowhiggs/dat/br/4fermions_llll.txt
yellowhiggs/dat/br/4fermions_llqq_qqqq.txt
yellowhiggs/dat/xs/13/bbh.txt
yellowhiggs/dat/xs/13/ggf.txt
yellowhiggs/dat/xs/13/tth.txt
yellowhiggs/dat/xs/13/vbf.txt
yellowhiggs/dat/xs/13/wh.txt
yellowhiggs/dat/xs/13/zh.txt
yellowhiggs/dat/xs/14/ggf.txt
yellowhiggs/dat/xs/14/tth.txt
yellowhiggs/dat/xs/14/vbf.txt
yellowhiggs/dat/xs/14/wh.txt
yellowhiggs/dat/xs/14/zh.txt
yellowhiggs/dat/xs/7/ggf.txt
yellowhiggs/dat/xs/7/tth.txt
yellowhiggs/dat/xs/7/vbf.txt
yellowhiggs/dat/xs/7/wh.txt
yellowhiggs/dat/xs/7/zh.txt
yellowhiggs/dat/xs/8/ggf.txt
yellowhiggs/dat/xs/8/tth.txt
yellowhiggs/dat/xs/8/vbf.txt
yellowhiggs/dat/xs/8/wh.txt
yellowhiggs/dat/xs/8/zh.txt