Metadata-Version: 1.1
Name: yellowhiggs
Version: 3.1.0
Summary: Interface for the CERN Yellow Report
Home-page: https://github.com/ndawe/yellowhiggs
Author: Noel Dawe
Author-email: noel.dawe@cern.ch
License: GPLv3
Download-URL: http://pypi.python.org/packages/source/y/yellowhiggs/yellowhiggs-3.1.0.tar.gz
Platform: UNKNOWN
Classifier: Programming Language :: Python
Classifier: Topic :: Utilities
Classifier: Operating System :: POSIX :: Linux
Classifier: Development Status :: 3 - Alpha
Classifier: Intended Audience :: Science/Research
Classifier: Intended Audience :: Developers
Classifier: License :: OSI Approved :: GNU General Public License (GPL)
